filehelpers/__init__.py
python_filehelpers-1.0.6.dist-info/DESCRIPTION.rst
python_filehelpers-1.0.6.dist-info/METADATA
python_filehelpers-1.0.6.dist-info/RECORD
python_filehelpers-1.0.6.dist-info/WHEEL
python_filehelpers-1.0.6.dist-info/metadata.json
python_filehelpers-1.0.6.dist-info/top_level.txt
