Metadata-Version: 2.0
Name: python-filehelpers
Version: 1.0.6
Summary: A set of various file helpers.
Home-page: https://github.com/ipsod/python_filehelpers
Author: Dusty Gamble
Author-email: dusty.gamble@gmail.com
License: MIT
Platform: UNKNOWN
Classifier: Topic :: Utilities
Classifier: Topic :: Text Processing
Classifier: Intended Audience :: Developers
Classifier: Operating System :: OS Independent
Classifier: Programming Language :: Python :: 3
Classifier: License :: OSI Approved :: MIT License
